plaster_dynaconf/__init__.py
plaster_dynaconf/loader.py
plaster_dynaconf-0.1.0.dist-info/LICENSE
plaster_dynaconf-0.1.0.dist-info/METADATA
plaster_dynaconf-0.1.0.dist-info/WHEEL
plaster_dynaconf-0.1.0.dist-info/entry_points.txt
plaster_dynaconf-0.1.0.dist-info/top_level.txt
plaster_dynaconf-0.1.0.dist-info/RECORD
