Metadata-Version: 2.1
Name: plaster-dynaconf
Version: 0.1.0
Summary: A plaster plugin to configure pyramid app with Dynaconf
Home-page: https://gitlab.com/lobi/plaster-dynaconf
Author: Sebastian Lobinger
Author-email: software.slobinger@t-online.de
License: UNKNOWN
Platform: UNKNOWN
Requires-Python: >=3.6
License-File: LICENSE
Requires-Dist: Dynaconf (>=3.0)
Requires-Dist: plaster (>=1.0)
